{
    "format_version": "1.16",
    "minecraft:recipe_shaped": {
        "description": {
            "identifier": "mabe:helmet_craftor_3"
        },
        "key": {
            "c": {
                "item": "mabe:magia_quill_pen"
            },
            "d": {
                "item": "mabe:abyss_gel"
            },
            "e": {
                "item": "mabe:helmet_craftor_2"
            },
            "f": {
                "item": "minecraft:oxidized_copper"
            },
            "g": {
                "item": "minecraft:magma"
            },
            "h": {
                "item": "mabe:magia_light_crystal_block"
            },
            "i": {
                "item": "minecraft:diamond_block"
            }
        },
        "pattern": [
            "  c",
            "def",
            "ghi"
        ],
        "priority": 1,
        "result": {
            "count": 1,
            "item": "mabe:helmet_craftor_3"
        },
        "tags": [
            "crafting_table"
        ]
    }
}
