{
    "format_version": "1.16",
    "minecraft:recipe_shaped": {
        "description": {
            "identifier": "mabe:organ_craftor_3"
        },
        "key": {
            "c": {
                "item": "mabe:magia_quill_pen"
            },
            "d": {
                "item": "minecraft:diamond"
            },
            "e": {
                "item": "mabe:organ_craftor_2"
            },
            "f": {
                "item": "mabe:organ_catalyst_green"
            },
            "g": {
                "item": "mabe:fallen_star"
            },
            "h": {
                "item": "mabe:organ_wing_yellow"
            }
        },
        "pattern": [
            "  c",
            "ded",
            "gfh"
        ],
        "priority": 1,
        "result": {
            "count": 1,
            "item": "mabe:organ_craftor_3"
        },
        "tags": [
            "crafting_table"
        ]
    }
}
