{
	"format_version": "1.8.0",
	"animations": {
		"animation.lavasta.walk": {
			"anim_time_update": "query.modified_distance_moved",
			"bones": {
				"rarm1_1": {
					"rotation": [0, "-math.abs(math.cos(query.anim_time * 76.34 + 90 * 0) * 22.92)", "math.abs(math.sin(query.anim_time * 38.17 + 90 * 0) * 22.92)"]
				},
				"larm1_1": {
					"rotation": [0, "math.abs(math.cos(query.anim_time * 76.34 + 90 * 0) * 22.92)", "-math.abs(math.sin(query.anim_time * 38.17 + 90 * 0) * 22.92)"]
				},
				"rarm2_1": {
					"rotation": [0, "-math.abs(math.cos(query.anim_time * 76.34 + 90 * 1) * 22.92)", "math.abs(math.sin(query.anim_time * 38.17 + 90 * 1) * 22.92)"]
				},
				"larm2_1": {
					"rotation": [0, "math.abs(math.cos(query.anim_time * 76.34 + 90 * 1) * 22.92)", "-math.abs(math.sin(query.anim_time * 38.17 + 90 * 1) * 22.92)"]
				},
				"rarm3_1": {
					"rotation": [0, "-math.abs(math.cos(query.anim_time * 76.34 + 90 * 2) * 22.92)", "math.abs(math.sin(query.anim_time * 38.17 + 90 * 2) * 22.92)"]
				},
				"larm3_1": {
					"rotation": [0, "math.abs(math.cos(query.anim_time * 76.34 + 90 * 2) * 22.92)", "-math.abs(math.sin(query.anim_time * 38.17 + 90 * 2) * 22.92)"]
				}
			},
			"loop": true
		},
		"animation.lavasta.swim": {
			"loop": true,
			"animation_length": 1,
			"override_previous_animation": true,
			"bones": {
				"head": {
					"rotation": {
						"0.0": [0, 0, 0],
						"0.25": [20, 0, 0],
						"0.5": [0, 0, 0],
						"0.75": [-20, 0, 0],
						"1.0": [0, 0, 0]
					},
					"position": {
						"0.0": [0, 4, 0],
						"0.5": [0, -4, 0],
						"1.0": [0, 4, 0]
					}
				},
				"body1": {
					"rotation": {
						"0.0": [-30, 0, 0],
						"0.25": [0, 0, 0],
						"0.5": [30, 0, 0],
						"0.75": [0, 0, 0],
						"1.0": [-30, 0, 0]
					}
				},
				"body2": {
					"rotation": {
						"0.0": [0, 0, 0],
						"0.25": [-40, 0, 0],
						"0.5": [0, 0, 0],
						"0.75": [40, 0, 0],
						"1.0": [0, 0, 0]
					}
				},
				"body3": {
					"rotation": {
						"0.0": [50, 0, 0],
						"0.25": [0, 0, 0],
						"0.5": [-50, 0, 0],
						"0.75": [0, 0, 0],
						"1.0": [50, 0, 0]
					}
				},
				"body4": {
					"rotation": {
						"0.0": [0, 0, 0],
						"0.25": [60, 0, 0],
						"0.5": [0, 0, 0],
						"0.75": [-60, 0, 0],
						"1.0": [0, 0, 0]
					}
				},
				"rwing1": {
					"rotation": {
						"0.0": [0, 0, 15],
						"0.5": [0, 0, -15],
						"1.0": [0, 0, 15]
					}
				},
				"lwing1": {
					"rotation": {
						"0.0": [0, 0, -15],
						"0.5": [0, 0, 15],
						"1.0": [0, 0, -15]
					}
				},
				"lwing2": {
					"rotation": {
						"0.0": [0, 0, -5],
						"0.1667": [0, 0, -15],
						"0.6833": [0, 0, 15],
						"1.0": [0, 0, -5]
					}
				},
				"rwing2": {
					"rotation": {
						"0.0": [0, 0, 5],
						"0.1667": [0, 0, 15],
						"0.6833": [0, 0, -15],
						"1.0": [0, 0, 5]
					}
				},
				"lwing3": {
					"rotation": {
						"0.0": [0, 0, 5],
						"0.3667": [0, 0, -15],
						"0.8333": [0, 0, 15],
						"1.0": [0, 0, 5]
					}
				},
				"rwing3": {
					"rotation": {
						"0.0": [0, 0, -5],
						"0.3667": [0, 0, 15],
						"0.8333": [0, 0, -15],
						"1.0": [0, 0, -5]
					}
				},
				"rwing4": {
					"rotation": {
						"0.0": [0, 0, -15],
						"0.5167": [0, 0, 15],
						"1.0": [0, 0, -15]
					}
				},
				"lwing4": {
					"rotation": {
						"0.0": [0, 0, 15],
						"0.5167": [0, 0, -15],
						"1.0": [0, 0, 15]
					}
				},
				"body5": {
					"rotation": {
						"0.0": [-70, 0, 0],
						"0.25": [0, 0, 0],
						"0.5": [70, 0, 0],
						"0.75": [0, 0, 0],
						"1.0": [-70, 0, 0]
					}
				},
				"lwing5": {
					"rotation": {
						"0.0": [0, 0, -5],
						"0.1667": [0, 0, -15],
						"0.6833": [0, 0, 15],
						"1.0": [0, 0, -5]
					}
				},
				"rwing5": {
					"rotation": {
						"0.0": [0, 0, 5],
						"0.1667": [0, 0, 15],
						"0.6833": [0, 0, -15],
						"1.0": [0, 0, 5]
					}
				},
				"body6": {
					"rotation": {
						"0.0": [0, 0, 0],
						"0.25": [-80, 0, 0],
						"0.5": [0, 0, 0],
						"0.75": [80, 0, 0],
						"1.0": [0, 0, 0]
					}
				},
				"lwing6": {
					"rotation": {
						"0.0": [0, 0, 5],
						"0.3667": [0, 0, -15],
						"0.8333": [0, 0, 15],
						"1.0": [0, 0, 5]
					}
				},
				"rwing6": {
					"rotation": {
						"0.0": [0, 0, -5],
						"0.3667": [0, 0, 15],
						"0.8333": [0, 0, -15],
						"1.0": [0, 0, -5]
					}
				}
			}
		},
		"animation.lavasta.stand_pose": {
			"loop": "hold_on_last_frame",
			"animation_length": 0.5,
			"bones": {
				"rarm1_1": {
					"rotation": {
						"0.0": [0, 90, -90],
						"0.5": [60, 0, -75]
					}
				},
				"rarm1_2": {
					"rotation": {
						"0.0": [0, 0, 180],
						"0.5": [0, 0, 130]
					}
				},
				"rarm1_3": {
					"rotation": {
						"0.0": [5, 0, -180],
						"0.5": [0, 0, -120]
					}
				},
				"rarm2_1": {
					"rotation": {
						"0.0": [0, 90, -90],
						"0.5": [0, 0, -75]
					}
				},
				"rarm2_2": {
					"rotation": {
						"0.0": [0, 0, 180],
						"0.5": [0, 0, 130]
					}
				},
				"rarm2_3": {
					"rotation": {
						"0.0": [3, 0, -180],
						"0.5": [0, 0, -120]
					}
				},
				"rarm3_1": {
					"rotation": {
						"0.0": [0, 90, -90],
						"0.5": [-40, 0, -75]
					}
				},
				"rarm3_2": {
					"rotation": {
						"0.0": [0, 0, 180],
						"0.5": [0, 0, 130]
					}
				},
				"rarm3_3": {
					"rotation": {
						"0.0": [-5, 0, -180],
						"0.5": [0, 0, -120]
					}
				},
				"larm1_1": {
					"rotation": {
						"0.0": [0, -90, 90],
						"0.5": [60, 0, 75]
					}
				},
				"larm1_2": {
					"rotation": {
						"0.0": [0, 0, -180],
						"0.5": [0, 0, -130]
					}
				},
				"larm1_3": {
					"rotation": {
						"0.0": [5, 0, 180],
						"0.5": [0, 0, 120]
					}
				},
				"larm2_1": {
					"rotation": {
						"0.0": [0, -90, 90],
						"0.5": [0, 0, 75]
					}
				},
				"larm2_2": {
					"rotation": {
						"0.0": [0, 0, -180],
						"0.5": [0, 0, -130]
					}
				},
				"larm2_3": {
					"rotation": {
						"0.0": [3, 0, 180],
						"0.5": [0, 0, 120]
					}
				},
				"larm3_1": {
					"rotation": {
						"0.0": [0, -90, 90],
						"0.5": [-40, 0, 75]
					}
				},
				"larm3_2": {
					"rotation": {
						"0.0": [0, 0, -180],
						"0.5": [0, 0, -130]
					}
				},
				"larm3_3": {
					"rotation": {
						"0.0": [-5, 0, 180],
						"0.5": [0, 0, 120]
					}
				},
				"head": {
					"rotation": {
						"0.0": [0, 0, 0],
						"0.5": [0, 0, 0]
					},
					"position": {
						"0.0": [0, 0, 0],
						"0.5": [0, 5, 0]
					}
				},
				"body1": {
					"rotation": {
						"0.0": [0, 0, 0],
						"0.5": [-10, 0, 0]
					}
				},
				"body2": {
					"rotation": {
						"0.0": [0, 0, 0],
						"0.5": [-10, 0, 0]
					}
				},
				"body3": {
					"rotation": {
						"0.0": [0, 0, 0],
						"0.5": [10, 0, 0]
					}
				},
				"body4": {
					"rotation": {
						"0.0": [0, 0, 0],
						"0.5": [5, 0, 0]
					}
				},
				"body5": {
					"rotation": {
						"0.0": [0, 0, 0],
						"0.5": [2.5, 0, 0]
					}
				},
				"body6": {
					"rotation": {
						"0.0": [0, 0, 0],
						"0.5": [0, 0, 0]
					}
				}
			}
		},
		"animation.lavasta.swim_pose": {
			"loop": "hold_on_last_frame",
			"animation_length": 0.5,
			"bones": {
				"head": {
					"rotation": {
						"0.0": [0, 0, 0],
						"0.5": [0, 0, 0]
					},
					"position": {
						"0.0": [0, 5, 0],
						"0.5": [0, 0, 0]
					}
				},
				"body1": {
					"rotation": {
						"0.0": [-10, 0, 0],
						"0.5": [0, 0, 0]
					}
				},
				"body2": {
					"rotation": {
						"0.0": [-10, 0, 0],
						"0.5": [0, 0, 0]
					}
				},
				"body3": {
					"rotation": {
						"0.0": [10, 0, 0],
						"0.5": [0, 0, 0]
					}
				},
				"body4": {
					"rotation": {
						"0.0": [5, 0, 0],
						"0.5": [0, 0, 0]
					}
				},
				"body5": {
					"rotation": {
						"0.0": [2.5, 0, 0],
						"0.5": [0, 0, 0]
					}
				},
				"body6": {
					"rotation": {
						"0.0": [0, 0, 0],
						"0.5": [0, 0, 0]
					}
				},
				"rarm1_1": {
					"rotation": {
						"0.0": [60, 0, -75],
						"0.5": [0, 90, -90]
					}
				},
				"rarm1_2": {
					"rotation": {
						"0.0": [0, 0, 130],
						"0.5": [0, 0, 180]
					}
				},
				"rarm1_3": {
					"rotation": {
						"0.0": [0, 0, -120],
						"0.5": [5, 0, -180]
					}
				},
				"rarm2_1": {
					"rotation": {
						"0.0": [0, 0, -75],
						"0.5": [0, 90, -90]
					}
				},
				"rarm2_2": {
					"rotation": {
						"0.0": [0, 0, 130],
						"0.5": [0, 0, 180]
					}
				},
				"rarm2_3": {
					"rotation": {
						"0.0": [0, 0, -120],
						"0.5": [3, 0, -180]
					}
				},
				"rarm3_1": {
					"rotation": {
						"0.0": [-40, 0, -75],
						"0.5": [0, 90, -90]
					}
				},
				"rarm3_2": {
					"rotation": {
						"0.0": [0, 0, 130],
						"0.5": [0, 0, 180]
					}
				},
				"rarm3_3": {
					"rotation": {
						"0.0": [0, 0, -120],
						"0.5": [-5, 0, -180]
					}
				},
				"larm1_1": {
					"rotation": {
						"0.0": [60, 0, 75],
						"0.5": [0, -90, 90]
					}
				},
				"larm1_2": {
					"rotation": {
						"0.0": [0, 0, -130],
						"0.5": [0, 0, -180]
					}
				},
				"larm1_3": {
					"rotation": {
						"0.0": [0, 0, 120],
						"0.5": [5, 0, 180]
					}
				},
				"larm2_1": {
					"rotation": {
						"0.0": [0, 0, 75],
						"0.5": [0, -90, 90]
					}
				},
				"larm2_2": {
					"rotation": {
						"0.0": [0, 0, -130],
						"0.5": [0, 0, -180]
					}
				},
				"larm2_3": {
					"rotation": {
						"0.0": [0, 0, 120],
						"0.5": [3, 0, 180]
					}
				},
				"larm3_1": {
					"rotation": {
						"0.0": [-40, 0, 75],
						"0.5": [0, -90, 90]
					}
				},
				"larm3_2": {
					"rotation": {
						"0.0": [0, 0, -130],
						"0.5": [0, 0, -180]
					}
				},
				"larm3_3": {
					"rotation": {
						"0.0": [0, 0, 120],
						"0.5": [-5, 0, 180]
					}
				}
			}
		},
		"animation.lavasta.curve": {
			"loop": true,
			"bones": {
				"head": {
					"position": ["query.target_y_rotation * 64 / 180", 0, 0],
					"rotation": [0, "-query.target_y_rotation", 0]
				},
				"body1": {
					"rotation": [0, "query.target_y_rotation / 10", 0]
				},
				"body2": {
					"rotation": [0, "query.target_y_rotation / 10", 0]
				},
				"body3": {
					"rotation": [0, "query.target_y_rotation / 10", 0]
				},
				"body4": {
					"rotation": [0, "query.target_y_rotation / 10", 0]
				},
				"body5": {
					"rotation": [0, "query.target_y_rotation / 10", 0]
				},
				"body6": {
					"rotation": [0, "query.target_y_rotation / 10", 0]
				}
			}
		}
	}
}